pi_utils/__init__.py
pi_utils/pielasticsearch/__init__.py
pi_utils/pilogging/__init__.py
pi_utils/pitrading/__init__.py
pi_utils/pitrading/holidays.py
pi_utils/pitrading/instrument.py
pi_utils-0.9.2.dist-info/METADATA
pi_utils-0.9.2.dist-info/WHEEL
pi_utils-0.9.2.dist-info/top_level.txt
pi_utils-0.9.2.dist-info/RECORD
