Metadata-Version: 2.4
Name: pi_utils
Version: 0.9.2
Summary: pi utils
Author: dianyao
Author-email: raiden@dianyao.ai
Dynamic: author
Dynamic: author-email
Dynamic: description
Dynamic: description-content-type
Dynamic: summary
